Implementation/__init__.py
Implementation/main.py
Implementation/Flask/__init__.py
Implementation/Flask/app.py
Implementation/Flask/app_backup.py
Implementation/Relocation/InformationPOIs.py
Implementation/Relocation/POIRankings.py
Implementation/Relocation/StartingPOI.py
Implementation/Relocation/__init__.py
g09_cps_relocation-1.0.0.dist-info/LICENSE.txt
g09_cps_relocation-1.0.0.dist-info/METADATA
g09_cps_relocation-1.0.0.dist-info/WHEEL
g09_cps_relocation-1.0.0.dist-info/top_level.txt
g09_cps_relocation-1.0.0.dist-info/RECORD
