Metadata-Version: 2.1
Name: g09-cps-relocation
Version: 1.0.0
Summary: A python client library used to get a quick overview between the different libraries of g09_CPS_relocation.
Home-page: https://gitlab.dke.univie.ac.at/edu-semtech/semtec_ws2020/g09_cps_relocation
Author: Anton La Fontaine, Lukas Lehnert
Author-email: a01351415@unet.univie.ac.at
License: UNKNOWN
Platform: UNKNOWN
Requires-Python: >=3.7
Requires-Dist: Flask
Requires-Dist: paramiko
Requires-Dist: Owlready2
Requires-Dist: flaskwebgui
Requires-Dist: Werkzeug
Requires-Dist: rdflib
Requires-Dist: requests
